LICENSE
README.md
sync2folders/__init__.py
sync2folders/__main__.py
sync2folders-1.0.2.dist-info/entry_points.txt
sync2folders-1.0.2.dist-info/LICENSE
sync2folders-1.0.2.dist-info/METADATA
sync2folders-1.0.2.dist-info/WHEEL
sync2folders-1.0.2.dist-info/RECORD
