Metadata-Version: 2.1
Name: sync2folders
Version: 1.0.2
Summary: Synchronizes source and replica folders
Home-page: https://github.com/ivanSantos16/sync2folders
License: MIT
Keywords: sync,folders,synchronize
Author: ivanSantos16
Author-email: ivan.rafa.16@gmail.com
Maintainer: ivanSantos16
Maintainer-email: ivan.rafa.16@gmail.com
Requires-Python: >=3.10
Classifier: Development Status :: 3 - Alpha
Classifier: Environment :: Console
Classifier: Intended Audience :: Developers
Classifier: License :: OSI Approved :: MIT License
Classifier: Natural Language :: English
Classifier: Operating System :: OS Independent
Classifier: Programming Language :: Python :: 3
Classifier: Programming Language :: Python :: 3.10
Classifier: Programming Language :: Python :: 3.11
Classifier: Programming Language :: Python :: 3.10
Classifier: Topic :: Software Development :: Libraries :: Python Modules
Classifier: Topic :: Utilities
Requires-Dist: markdown (>=3.3.4)
Project-URL: Repository, https://github.com/ivanSantos16/sync2folders
